{"Code":"TEC01","Description":"Plan 2019","YearOfValidity":2020,"Major":"Tecnicatura en Desarrollo de Software","University":"UPE - Universidad Provincial de Ezeiza","Subjects":[{"IdSubject":1,"Code":null,"Name":"SW y los Nuevos Escenarios","TeachingHours":6},{"IdSubject":2,"Code":null,"Name":"Programación en Tiempo Real","TeachingHours":5},{"IdSubject":3,"Code":null,"Name":"Técnicas de Programación","TeachingHours":6},{"IdSubject":4,"Code":null,"Name":"Programación Web","TeachingHours":8},{"IdSubject":5,"Code":null,"Name":"Sistemas Operativos","TeachingHours":4}]}